pypi_release
