Metadata-Version: 1.0
Name: pypi-release
Version: 1.0.1
Summary: Release pypi package to Pinrepo
Home-page: https://github.com/pinterest/pinrepo
Author: Baogang Song
Author-email: baogang@pinterest.com
License: Apache License 2.0
Keywords: pypi pinrepo pinterest artifact repository
Platform: UNKNOWN
